{
  "id": "5ad12f83-3c93-4c0e-8d7d-53c899fb0421",
  "prevId": "00000000-0000-0000-0000-000000000000",
  "version": "7",
  "dialect": "postgresql",
  "tables": {
    "public.contact_inquiries": {
      "name": "contact_inquiries",
      "schema": "",
      "columns": {
        "id": {
          "name": "id",
          "type": "uuid",
          "primaryKey": true,
          "notNull": true,
          "default": "gen_random_uuid()"
        },
        "name": {
          "name": "name",
          "type": "varchar(150)",
          "primaryKey": false,
          "notNull": true
        },
        "phone_number": {
          "name": "phone_number",
          "type": "varchar(20)",
          "primaryKey": false,
          "notNull": true
        },
        "email": {
          "name": "email",
          "type": "varchar(255)",
          "primaryKey": false,
          "notNull": false
        },
        "city": {
          "name": "city",
          "type": "varchar(100)",
          "primaryKey": false,
          "notNull": true
        },
        "state": {
          "name": "state",
          "type": "varchar(100)",
          "primaryKey": false,
          "notNull": true
        },
        "cafe_name": {
          "name": "cafe_name",
          "type": "varchar(255)",
          "primaryKey": false,
          "notNull": false
        },
        "using_software": {
          "name": "using_software",
          "type": "boolean",
          "primaryKey": false,
          "notNull": true
        },
        "message": {
          "name": "message",
          "type": "text",
          "primaryKey": false,
          "notNull": false
        },
        "status": {
          "name": "status",
          "type": "inquiry_status",
          "typeSchema": "public",
          "primaryKey": false,
          "notNull": true,
          "default": "'PENDING'"
        },
        "created_at": {
          "name": "created_at",
          "type": "timestamp with time zone",
          "primaryKey": false,
          "notNull": true,
          "default": "now()"
        },
        "updated_at": {
          "name": "updated_at",
          "type": "timestamp with time zone",
          "primaryKey": false,
          "notNull": true,
          "default": "now()"
        }
      },
      "indexes": {},
      "foreignKeys": {},
      "compositePrimaryKeys": {},
      "uniqueConstraints": {},
      "policies": {},
      "checkConstraints": {},
      "isRLSEnabled": false
    },
    "public.feature": {
      "name": "feature",
      "schema": "",
      "columns": {
        "id": {
          "name": "id",
          "type": "uuid",
          "primaryKey": true,
          "notNull": true,
          "default": "gen_random_uuid()"
        },
        "image_url": {
          "name": "image_url",
          "type": "text",
          "primaryKey": false,
          "notNull": true
        },
        "title": {
          "name": "title",
          "type": "varchar(255)",
          "primaryKey": false,
          "notNull": true
        },
        "description": {
          "name": "description",
          "type": "varchar(750)",
          "primaryKey": false,
          "notNull": true
        },
        "content": {
          "name": "content",
          "type": "text",
          "primaryKey": false,
          "notNull": true
        },
        "created_at": {
          "name": "created_at",
          "type": "timestamp with time zone",
          "primaryKey": false,
          "notNull": true,
          "default": "now()"
        },
        "updated_at": {
          "name": "updated_at",
          "type": "timestamp with time zone",
          "primaryKey": false,
          "notNull": true,
          "default": "now()"
        }
      },
      "indexes": {},
      "foreignKeys": {},
      "compositePrimaryKeys": {},
      "uniqueConstraints": {},
      "policies": {},
      "checkConstraints": {},
      "isRLSEnabled": false
    },
    "public.pricing_plan": {
      "name": "pricing_plan",
      "schema": "",
      "columns": {
        "id": {
          "name": "id",
          "type": "uuid",
          "primaryKey": true,
          "notNull": true,
          "default": "gen_random_uuid()"
        },
        "name": {
          "name": "name",
          "type": "varchar(100)",
          "primaryKey": false,
          "notNull": true
        },
        "description": {
          "name": "description",
          "type": "varchar(750)",
          "primaryKey": false,
          "notNull": false
        },
        "price": {
          "name": "price",
          "type": "numeric(10, 2)",
          "primaryKey": false,
          "notNull": true
        },
        "currency": {
          "name": "currency",
          "type": "varchar(10)",
          "primaryKey": false,
          "notNull": true,
          "default": "'INR'"
        },
        "billing_cycle": {
          "name": "billing_cycle",
          "type": "billing_cycle",
          "typeSchema": "public",
          "primaryKey": false,
          "notNull": true
        },
        "features": {
          "name": "features",
          "type": "jsonb",
          "primaryKey": false,
          "notNull": false
        },
        "is_popular": {
          "name": "is_popular",
          "type": "boolean",
          "primaryKey": false,
          "notNull": true,
          "default": false
        },
        "has_first_purchase_discount": {
          "name": "has_first_purchase_discount",
          "type": "boolean",
          "primaryKey": false,
          "notNull": true,
          "default": true
        },
        "first_purchase_discount_pct": {
          "name": "first_purchase_discount_pct",
          "type": "integer",
          "primaryKey": false,
          "notNull": true,
          "default": 50
        },
        "created_at": {
          "name": "created_at",
          "type": "timestamp with time zone",
          "primaryKey": false,
          "notNull": true,
          "default": "now()"
        },
        "updated_at": {
          "name": "updated_at",
          "type": "timestamp with time zone",
          "primaryKey": false,
          "notNull": true,
          "default": "now()"
        }
      },
      "indexes": {},
      "foreignKeys": {},
      "compositePrimaryKeys": {},
      "uniqueConstraints": {},
      "policies": {},
      "checkConstraints": {
        "discount_pct_range": {
          "name": "discount_pct_range",
          "value": "\"pricing_plan\".\"first_purchase_discount_pct\" >= 0 AND \"pricing_plan\".\"first_purchase_discount_pct\" <= 100"
        }
      },
      "isRLSEnabled": false
    }
  },
  "enums": {
    "public.billing_cycle": {
      "name": "billing_cycle",
      "schema": "public",
      "values": [
        "MONTHLY",
        "QUARTERLY",
        "YEARLY"
      ]
    },
    "public.inquiry_status": {
      "name": "inquiry_status",
      "schema": "public",
      "values": [
        "PENDING",
        "CONTACTED",
        "QUALIFIED",
        "CLOSED"
      ]
    }
  },
  "schemas": {},
  "sequences": {},
  "roles": {},
  "policies": {},
  "views": {},
  "_meta": {
    "columns": {},
    "schemas": {},
    "tables": {}
  }
}